GrafanaTimeConverter/__init__.py
GrafanaTimeConverter/convert.py
grafana_time_converter-0.0.1.dist-info/LICENSE
grafana_time_converter-0.0.1.dist-info/METADATA
grafana_time_converter-0.0.1.dist-info/WHEEL
grafana_time_converter-0.0.1.dist-info/top_level.txt
grafana_time_converter-0.0.1.dist-info/RECORD
