Metadata-Version: 2.1
Name: grafana-time-converter
Version: 0.0.1
Summary: Convert grafana timeranges
Home-page: https://github.com/voyzark/grafana-time-converter
Author: Jan Zwirner
Author-email: jan.zwirner@yahoo.de
License: UNKNOWN
Keywords: python,grafana
Platform: UNKNOWN
Classifier: Development Status :: 1 - Planning
Classifier: Intended Audience :: Developers
Classifier: Programming Language :: Python :: 3
Classifier: Operating System :: Unix
Classifier: Operating System :: MacOS :: MacOS X
Classifier: Operating System :: Microsoft :: Windows
